codebylang/verilog/primer/src/counter.v
module counter(out,clk,rst);
input clk,rst;
output reg[3:0] out ;

always @(posedge clk)
begin
	if(rst)
		out<=0;
	else
		out<=out+1;
end
endmodule

codebylang/verilog/primer/src/counter_top.v
`timescale 100ns/1ns
module counter_top;
reg clk=0;
reg rst;
wire[3:0] out;

parameter vcd="counter.vcd";

counter c(out,clk,rst);

initial 
	$dumpfile(vcd); 
initial
	$dumpvars(0,counter_top);

always
	#5 clk=~clk;


initial 
begin
	rst=1;
	#10 
	rst=0;



	#1000 
	$finish;
end 
endmodule

codebylang/verilog/primer/src/counter.vcd
$date
	Mon Sep  5 19:14:52 2016
$end
$version
	Icarus Verilog
$end
$timescale
	1ns
$end
$scope module counter_top $end
$var wire 4 ! out [3:0] $end
$var reg 1 " clk $end
$var reg 1 # rst $end
$scope module c $end
$var wire 1 $ clk $end
$var wire 1 % rst $end
$var reg 4 & out [3:0] $end
$upscope $end
$upscope $end
$enddefinitions $end
#0
$dumpvars
bx &
1%
0$
1#
0"
bx !
$end
#500
b0 &
b0 !
1"
1$
#1000
0"
0$
0#
0%
#1500
b1 &
b1 !
1"
1$
#2000
0"
0$
#2500
b10 &
b10 !
1"
1$
#3000
0"
0$
#3500
b11 &
b11 !
1"
1$
#4000
0"
0$
#4500
b100 &
b100 !
1"
1$
#5000
0"
0$
#5500
b101 &
b101 !
1"
1$
#6000
0"
0$
#6500
b110 &
b110 !
1"
1$
#7000
0"
0$
#7500
b111 &
b111 !
1"
1$
#8000
0"
0$
#8500
b1000 &
b1000 !
1"
1$
#9000
0"
0$
#9500
b1001 &
b1001 !
1"
1$
#10000
0"
0$
#10500
b1010 &
b1010 !
1"
1$
#11000
0"
0$
#11500
b1011 &
b1011 !
1"
1$
#12000
0"
0$
#12500
b1100 &
b1100 !
1"
1$
#13000
0"
0$
#13500
b1101 &
b1101 !
1"
1$
#14000
0"
0$
#14500
b1110 &
b1110 !
1"
1$
#15000
0"
0$
#15500
b1111 &
b1111 !
1"
1$
#16000
0"
0$
#16500
b0 &
b0 !
1"
1$
#17000
0"
0$
#17500
b1 &
b1 !
1"
1$
#18000
0"
0$
#18500
b10 &
b10 !
1"
1$
#19000
0"
0$
#19500
b11 &
b11 !
1"
1$
#20000
0"
0$
#20500
b100 &
b100 !
1"
1$
#21000
0"
0$
#21500
b101 &
b101 !
1"
1$
#22000
0"
0$
#22500
b110 &
b110 !
1"
1$
#23000
0"
0$
#23500
b111 &
b111 !
1"
1$
#24000
0"
0$
#24500
b1000 &
b1000 !
1"
1$
#25000
0"
0$
#25500
b1001 &
b1001 !
1"
1$
#26000
0"
0$
#26500
b1010 &
b1010 !
1"
1$
#27000
0"
0$
#27500
b1011 &
b1011 !
1"
1$
#28000
0"
0$
#28500
b1100 &
b1100 !
1"
1$
#29000
0"
0$
#29500
b1101 &
b1101 !
1"
1$
#30000
0"
0$
#30500
b1110 &
b1110 !
1"
1$
#31000
0"
0$
#31500
b1111 &
b1111 !
1"
1$
#32000
0"
0$
#32500
b0 &
b0 !
1"
1$
#33000
0"
0$
#33500
b1 &
b1 !
1"
1$
#34000
0"
0$
#34500
b10 &
b10 !
1"
1$
#35000
0"
0$
#35500
b11 &
b11 !
1"
1$
#36000
0"
0$
#36500
b100 &
b100 !
1"
1$
#37000
0"
0$
#37500
b101 &
b101 !
1"
1$
#38000
0"
0$
#38500
b110 &
b110 !
1"
1$
#39000
0"
0$
#39500
b111 &
b111 !
1"
1$
#40000
0"
0$
#40500
b1000 &
b1000 !
1"
1$
#41000
0"
0$
#41500
b1001 &
b1001 !
1"
1$
#42000
0"
0$
#42500
b1010 &
b1010 !
1"
1$
#43000
0"
0$
#43500
b1011 &
b1011 !
1"
1$
#44000
0"
0$
#44500
b1100 &
b1100 !
1"
1$
#45000
0"
0$
#45500
b1101 &
b1101 !
1"
1$
#46000
0"
0$
#46500
b1110 &
b1110 !
1"
1$
#47000
0"
0$
#47500
b1111 &
b1111 !
1"
1$
#48000
0"
0$
#48500
b0 &
b0 !
1"
1$
#49000
0"
0$
#49500
b1 &
b1 !
1"
1$
#50000
0"
0$
#50500
b10 &
b10 !
1"
1$
#51000
0"
0$
#51500
b11 &
b11 !
1"
1$
#52000
0"
0$
#52500
b100 &
b100 !
1"
1$
#53000
0"
0$
#53500
b101 &
b101 !
1"
1$
#54000
0"
0$
#54500
b110 &
b110 !
1"
1$
#55000
0"
0$
#55500
b111 &
b111 !
1"
1$
#56000
0"
0$
#56500
b1000 &
b1000 !
1"
1$
#57000
0"
0$
#57500
b1001 &
b1001 !
1"
1$
#58000
0"
0$
#58500
b1010 &
b1010 !
1"
1$
#59000
0"
0$
#59500
b1011 &
b1011 !
1"
1$
#60000
0"
0$
#60500
b1100 &
b1100 !
1"
1$
#61000
0"
0$
#61500
b1101 &
b1101 !
1"
1$
#62000
0"
0$
#62500
b1110 &
b1110 !
1"
1$
#63000
0"
0$
#63500
b1111 &
b1111 !
1"
1$
#64000
0"
0$
#64500
b0 &
b0 !
1"
1$
#65000
0"
0$
#65500
b1 &
b1 !
1"
1$
#66000
0"
0$
#66500
b10 &
b10 !
1"
1$
#67000
0"
0$
#67500
b11 &
b11 !
1"
1$
#68000
0"
0$
#68500
b100 &
b100 !
1"
1$
#69000
0"
0$
#69500
b101 &
b101 !
1"
1$
#70000
0"
0$
#70500
b110 &
b110 !
1"
1$
#71000
0"
0$
#71500
b111 &
b111 !
1"
1$
#72000
0"
0$
#72500
b1000 &
b1000 !
1"
1$
#73000
0"
0$
#73500
b1001 &
b1001 !
1"
1$
#74000
0"
0$
#74500
b1010 &
b1010 !
1"
1$
#75000
0"
0$
#75500
b1011 &
b1011 !
1"
1$
#76000
0"
0$
#76500
b1100 &
b1100 !
1"
1$
#77000
0"
0$
#77500
b1101 &
b1101 !
1"
1$
#78000
0"
0$
#78500
b1110 &
b1110 !
1"
1$
#79000
0"
0$
#79500
b1111 &
b1111 !
1"
1$
#80000
0"
0$
#80500
b0 &
b0 !
1"
1$
#81000
0"
0$
#81500
b1 &
b1 !
1"
1$
#82000
0"
0$
#82500
b10 &
b10 !
1"
1$
#83000
0"
0$
#83500
b11 &
b11 !
1"
1$
#84000
0"
0$
#84500
b100 &
b100 !
1"
1$
#85000
0"
0$
#85500
b101 &
b101 !
1"
1$
#86000
0"
0$
#86500
b110 &
b110 !
1"
1$
#87000
0"
0$
#87500
b111 &
b111 !
1"
1$
#88000
0"
0$
#88500
b1000 &
b1000 !
1"
1$
#89000
0"
0$
#89500
b1001 &
b1001 !
1"
1$
#90000
0"
0$
#90500
b1010 &
b1010 !
1"
1$
#91000
0"
0$
#91500
b1011 &
b1011 !
1"
1$
#92000
0"
0$
#92500
b1100 &
b1100 !
1"
1$
#93000
0"
0$
#93500
b1101 &
b1101 !
1"
1$
#94000
0"
0$
#94500
b1110 &
b1110 !
1"
1$
#95000
0"
0$
#95500
b1111 &
b1111 !
1"
1$
#96000
0"
0$
#96500
b0 &
b0 !
1"
1$
#97000
0"
0$
#97500
b1 &
b1 !
1"
1$
#98000
0"
0$
#98500
b10 &
b10 !
1"
1$
#99000
0"
0$
#99500
b11 &
b11 !
1"
1$
#100000
0"
0$
#100500
b100 &
b100 !
1"
1$
